odoo/addons/website_odoo_debranding/README.rst
odoo/addons/website_odoo_debranding/__init__.py
odoo/addons/website_odoo_debranding/__manifest__.py
odoo/addons/website_odoo_debranding/static/description/icon.png
odoo/addons/website_odoo_debranding/templates/disable_odoo.xml
odoo11_addon_website_odoo_debranding-11.0.1.0.0.dist-info/DESCRIPTION.rst
odoo11_addon_website_odoo_debranding-11.0.1.0.0.dist-info/METADATA
odoo11_addon_website_odoo_debranding-11.0.1.0.0.dist-info/RECORD
odoo11_addon_website_odoo_debranding-11.0.1.0.0.dist-info/WHEEL
odoo11_addon_website_odoo_debranding-11.0.1.0.0.dist-info/metadata.json
odoo11_addon_website_odoo_debranding-11.0.1.0.0.dist-info/top_level.txt
